customplot/__init__.py
customplot/myfunctions.py
customplot-0.1.0.dist-info/METADATA
customplot-0.1.0.dist-info/WHEEL
customplot-0.1.0.dist-info/top_level.txt
customplot-0.1.0.dist-info/RECORD
