Metadata-Version: 2.1
Name: customplot
Version: 0.1.0
Summary: Custom plotting library based on matplotlib
Home-page: UNKNOWN
Author: Wout Haksteen
License: None
Platform: UNKNOWN
